symurbench/__init__.py
symurbench/benchmark.py
symurbench/constant.py
symurbench/feature_extractor.py
symurbench/metaloader.py
symurbench/music21_extractor.py
symurbench/retrieval.py
symurbench/utils.py
symurbench/abstract_tasks/__init__.py
symurbench/abstract_tasks/abstask.py
symurbench/abstract_tasks/classification_task.py
symurbench/abstract_tasks/retrieval_task.py
symurbench/default_configs/automl_multiclass_config.yaml
symurbench/default_configs/automl_multilabel_config.yaml
symurbench/default_configs/tasks_config.yaml
symurbench/metrics/__init__.py
symurbench/metrics/metric_value.py
symurbench/metrics/retrieval_scorer.py
symurbench/metrics/scorer.py
symurbench/metrics/sklearn_scorer.py
symurbench/tasks/ComposerClassificationASAP.py
symurbench/tasks/EmotionClassificationEMOPIA.py
symurbench/tasks/EmotionClassificationMIREX.py
symurbench/tasks/GenreClassificationMMD.py
symurbench/tasks/GenreClassificationWMTX.py
symurbench/tasks/InstrumentDetectionMMD.py
symurbench/tasks/ScorePerformanceRetrievalASAP.py
symurbench/tasks/__init__.py
symurbench-1.0.0.dist-info/METADATA
symurbench-1.0.0.dist-info/WHEEL
symurbench-1.0.0.dist-info/licenses/LICENSE
symurbench-1.0.0.dist-info/RECORD
