Metadata-Version: 2.4
Name: symurbench
Version: 1.0.0
Summary: SyMuRBench: Benchmark for symbolic music representations
Author: Peter Strepetov, Dmitrii Kovalev
License: MIT License
License-File: LICENSE
Keywords: artificial intelligence,midi,mir,music
Classifier: Intended Audience :: Developers
Classifier: Intended Audience :: Science/Research
Classifier: License :: OSI Approved :: MIT License
Classifier: Operating System :: OS Independent
Classifier: Programming Language :: Python
Classifier: Programming Language :: Python :: 3 :: Only
Classifier: Programming Language :: Python :: 3.8
Classifier: Programming Language :: Python :: 3.9
Classifier: Programming Language :: Python :: 3.10
Classifier: Programming Language :: Python :: 3.11
Classifier: Programming Language :: Python :: 3.12
Classifier: Topic :: Multimedia :: Sound/Audio :: MIDI
Classifier: Topic :: Scientific/Engineering :: Artificial Intelligence
Requires-Python: >=3.10.0
Requires-Dist: lightautoml==0.4.1
Requires-Dist: music21==9.1.0
Requires-Dist: numpy<2.0.0,>=1.22
Requires-Dist: pandas
Requires-Dist: pyarrow
Requires-Dist: scikit-learn
Requires-Dist: tqdm
Provides-Extra: docs
Requires-Dist: sphinx; extra == 'docs'
Requires-Dist: sphinx-markdown-builder==0.6.7; extra == 'docs'
Requires-Dist: sphinx-rtd-theme; extra == 'docs'
Provides-Extra: tests
Requires-Dist: pytest-cov; extra == 'tests'
